camel2karam/__about__.py
camel2karam/__init__.py
camel2karam/camel2jsonl.py
camel2karam/cli.py
camel2karam/converters/__init__.py
camel2karam/converters/base_converter.py
camel2karam/converters/csv2connlu.py
camel2karam/converters/csvsent2csvtok.py
camel2karam/converters/csvsent2onelettertag.py
camel2karam/converters/csvtok2csvsent.py
camel2karam/converters/jsonl2connlu.py
camel2karam/converters/jsonl2csv.py
camel2karam/converters/jsonl2webanno.py
camel2karam/converters/jsonl2xml.py
camel2karam/converters/tagset_convert.py
camel2karam-0.0.3.dist-info/METADATA
camel2karam-0.0.3.dist-info/WHEEL
camel2karam-0.0.3.dist-info/entry_points.txt
camel2karam-0.0.3.dist-info/licenses/LICENSE
camel2karam-0.0.3.dist-info/licenses/LICENSE.txt
camel2karam-0.0.3.dist-info/RECORD
