Metadata-Version: 2.3
Name: camel2karam
Version: 0.0.3
Project-URL: Homepage, https://github.com/CERES-Sorbonne/C2K
Project-URL: Documentation, https://github.com/CERES-Sorbonne/C2K#readme
Project-URL: Issues, https://github.com/CERES-Sorbonne/C2K/issues
Project-URL: Source, https://github.com/CERES-Sorbonne/C2K
Author-email: Marceau-h <pypi@marceau-h.fr>
Keywords: convert
Classifier: Development Status :: 4 - Beta
Classifier: Intended Audience :: Developers
Classifier: Intended Audience :: End Users/Desktop
Classifier: Intended Audience :: Information Technology
Classifier: Intended Audience :: Science/Research
Classifier: License :: OSI Approved :: GNU Affero General Public License v3 or later (AGPLv3+)
Classifier: Operating System :: OS Independent
Classifier: Programming Language :: Python
Classifier: Programming Language :: Python :: 3 :: Only
Classifier: Programming Language :: Python :: 3.10
Classifier: Programming Language :: Python :: 3.11
Classifier: Programming Language :: Python :: 3.12
Classifier: Programming Language :: Python :: 3.13
Classifier: Programming Language :: Python :: Implementation :: CPython
Classifier: Programming Language :: Python :: Implementation :: PyPy
Requires-Python: >=3.10
Requires-Dist: camel-tools
Requires-Dist: polars
Requires-Dist: tqdm
